[{
    "id": 1,
    "first_name": "Brietta",
    "last_name": "Toma",
    "email": "btoma0@dyndns.org",
    "Phone_number": "620-649-6121"
  }, {
    "id": 2,
    "first_name": "Denise",
    "last_name": "Harvison",
    "email": "dharvison1@biblegateway.com",
    "Phone_number": "977-991-6591"
  }, {
    "id": 3,
    "first_name": "Arlen",
    "last_name": "Dronsfield",
    "email": "adronsfield2@lycos.com",
    "Phone_number": "277-587-7119"
  }, {
    "id": 4,
    "first_name": "Malia",
    "last_name": "Antcliff",
    "email": "mantcliff3@netvibes.com",
    "Phone_number": "993-600-7485"
  }, {
    "id": 5,
    "first_name": "Vonni",
    "last_name": "Selwyne",
    "email": "vselwyne4@census.gov",
    "Phone_number": "378-302-3344"
  }, {
    "id": 6,
    "first_name": "Chris",
    "last_name": "Anfrey",
    "email": "canfrey5@elegantthemes.com",
    "Phone_number": "278-245-9908"
  }, {
    "id": 7,
    "first_name": "Vilhelmina",
    "last_name": "Hurdiss",
    "email": "vhurdiss6@sogou.com",
    "Phone_number": "969-854-8607"
  }, {
    "id": 8,
    "first_name": "Gonzales",
    "last_name": "Horry",
    "email": "ghorry7@netscape.com",
    "Phone_number": "601-638-7402"
  }, {
    "id": 9,
    "first_name": "Lowell",
    "last_name": "Wateridge",
    "email": "lwateridge8@usa.gov",
    "Phone_number": "969-381-2174"
  }, {
    "id": 10,
    "first_name": "Ginny",
    "last_name": "Marshland",
    "email": "gmarshland9@wp.com",
    "Phone_number": "278-670-5125"
  }, {
    "id": 11,
    "first_name": "Kelci",
    "last_name": "Carluccio",
    "email": "kcarluccioa@flickr.com",
    "Phone_number": "481-137-5256"
  }, {
    "id": 12,
    "first_name": "Cly",
    "last_name": "Plitz",
    "email": "cplitzb@columbia.edu",
    "Phone_number": "822-328-2268"
  }, {
    "id": 13,
    "first_name": "Umeko",
    "last_name": "Cromer",
    "email": "ucromerc@skyrock.com",
    "Phone_number": "616-548-5918"
  }, {
    "id": 14,
    "first_name": "Orrin",
    "last_name": "Pinnegar",
    "email": "opinnegard@google.ca",
    "Phone_number": "483-964-9103"
  }, {
    "id": 15,
    "first_name": "Dayna",
    "last_name": "Coye",
    "email": "dcoyee@bbb.org",
    "Phone_number": "837-202-1719"
  }, {
    "id": 16,
    "first_name": "Derron",
    "last_name": "Srutton",
    "email": "dsruttonf@cisco.com",
    "Phone_number": "822-913-9835"
  }, {
    "id": 17,
    "first_name": "Jeralee",
    "last_name": "Dobrowolski",
    "email": "jdobrowolskig@tripadvisor.com",
    "Phone_number": "148-990-5579"
  }, {
    "id": 18,
    "first_name": "Elmer",
    "last_name": "Rassell",
    "email": "erassellh@istockphoto.com",
    "Phone_number": "966-217-3850"
  }, {
    "id": 19,
    "first_name": "Courtney",
    "last_name": "Gerber",
    "email": "cgerberi@twitpic.com",
    "Phone_number": "640-972-4162"
  }, {
    "id": 20,
    "first_name": "Tami",
    "last_name": "Stillwell",
    "email": "tstillwellj@si.edu",
    "Phone_number": "393-471-2569"
  }, {
    "id": 21,
    "first_name": "Marika",
    "last_name": "Axton",
    "email": "maxtonk@adobe.com",
    "Phone_number": "103-787-2963"
  }, {
    "id": 22,
    "first_name": "Cairistiona",
    "last_name": "Hunsworth",
    "email": "chunsworthl@feedburner.com",
    "Phone_number": "851-815-9961"
  }, {
    "id": 23,
    "first_name": "Martelle",
    "last_name": "Nowland",
    "email": "mnowlandm@w3.org",
    "Phone_number": "727-420-8010"
  }, {
    "id": 24,
    "first_name": "Tadeas",
    "last_name": "Youles",
    "email": "tyoulesn@surveymonkey.com",
    "Phone_number": "929-106-5842"
  }, {
    "id": 25,
    "first_name": "Berke",
    "last_name": "Pattillo",
    "email": "bpattilloo@simplemachines.org",
    "Phone_number": "251-385-7021"
  }, {
    "id": 26,
    "first_name": "Nollie",
    "last_name": "Donnell",
    "email": "ndonnellp@unicef.org",
    "Phone_number": "340-721-7939"
  }, {
    "id": 27,
    "first_name": "Benedikta",
    "last_name": "Cassels",
    "email": "bcasselsq@jigsy.com",
    "Phone_number": "130-377-3238"
  }, {
    "id": 28,
    "first_name": "Philip",
    "last_name": "Hayle",
    "email": "phayler@salon.com",
    "Phone_number": "436-831-7028"
  }, {
    "id": 29,
    "first_name": "Nikaniki",
    "last_name": "Hucker",
    "email": "nhuckers@omniture.com",
    "Phone_number": "757-500-2114"
  }, {
    "id": 30,
    "first_name": "Laurice",
    "last_name": "Paddington",
    "email": "lpaddingtont@hugedomains.com",
    "Phone_number": "909-664-3736"
  }, {
    "id": 31,
    "first_name": "Laura",
    "last_name": "Ivey",
    "email": "liveyu@gnu.org",
    "Phone_number": "346-629-4006"
  }, {
    "id": 32,
    "first_name": "Randa",
    "last_name": "Wackly",
    "email": "rwacklyv@nydailynews.com",
    "Phone_number": "499-184-4048"
  }, {
    "id": 33,
    "first_name": "Peyton",
    "last_name": "Jeanneau",
    "email": "pjeanneauw@lulu.com",
    "Phone_number": "523-989-8155"
  }, {
    "id": 34,
    "first_name": "Filippo",
    "last_name": "Surplice",
    "email": "fsurplicex@bbc.co.uk",
    "Phone_number": "575-745-9149"
  }, {
    "id": 35,
    "first_name": "Reynard",
    "last_name": "Sobczak",
    "email": "rsobczaky@house.gov",
    "Phone_number": "998-330-2741"
  }, {
    "id": 36,
    "first_name": "Henriette",
    "last_name": "de Savery",
    "email": "hdesaveryz@npr.org",
    "Phone_number": "324-239-0428"
  }, {
    "id": 37,
    "first_name": "Emili",
    "last_name": "Buffy",
    "email": "ebuffy10@php.net",
    "Phone_number": "893-258-6531"
  }, {
    "id": 38,
    "first_name": "Merci",
    "last_name": "Blackwood",
    "email": "mblackwood11@a8.net",
    "Phone_number": "340-615-4274"
  }, {
    "id": 39,
    "first_name": "Case",
    "last_name": "Scramage",
    "email": "cscramage12@soup.io",
    "Phone_number": "829-984-4671"
  }, {
    "id": 40,
    "first_name": "Shaine",
    "last_name": "Husset",
    "email": "shusset13@webs.com",
    "Phone_number": "889-512-9954"
  }, {
    "id": 41,
    "first_name": "Lazarus",
    "last_name": "McKimmie",
    "email": "lmckimmie14@cbc.ca",
    "Phone_number": "857-845-8004"
  }, {
    "id": 42,
    "first_name": "Sandye",
    "last_name": "Sainz",
    "email": "ssainz15@naver.com",
    "Phone_number": "192-757-1205"
  }, {
    "id": 43,
    "first_name": "Evonne",
    "last_name": "Reolfo",
    "email": "ereolfo16@stumbleupon.com",
    "Phone_number": "259-361-6547"
  }, {
    "id": 44,
    "first_name": "Rustie",
    "last_name": "MacNeill",
    "email": "rmacneill17@studiopress.com",
    "Phone_number": "322-328-6514"
  }, {
    "id": 45,
    "first_name": "Keelia",
    "last_name": "Neylon",
    "email": "kneylon18@slate.com",
    "Phone_number": "833-895-7614"
  }, {
    "id": 46,
    "first_name": "Boone",
    "last_name": "Studman",
    "email": "bstudman19@microsoft.com",
    "Phone_number": "229-570-9925"
  }, {
    "id": 47,
    "first_name": "Russ",
    "last_name": "Niemiec",
    "email": "rniemiec1a@latimes.com",
    "Phone_number": "268-173-4674"
  }, {
    "id": 48,
    "first_name": "Angelica",
    "last_name": "Vasilchenko",
    "email": "avasilchenko1b@illinois.edu",
    "Phone_number": "383-971-4502"
  }, {
    "id": 49,
    "first_name": "Tomasina",
    "last_name": "Balharry",
    "email": "tbalharry1c@canalblog.com",
    "Phone_number": "859-533-4173"
  }, {
    "id": 50,
    "first_name": "Miner",
    "last_name": "Malletratt",
    "email": "mmalletratt1d@ovh.net",
    "Phone_number": "711-306-2239"
  }]
  